README.md
setup.py
gsxws/__init__.py
gsxws/comms.py
gsxws/comptia.py
gsxws/content.py
gsxws/core.py
gsxws/diagnostics.py
gsxws/escalations.py
gsxws/langs.json
gsxws/lookups.py
gsxws/objectify.py
gsxws/orders.py
gsxws/parts.py
gsxws/products.py
gsxws/products.yaml
gsxws/repairs.py
gsxws/returns.py
gsxws/utils.py
gsxws.egg-info/PKG-INFO
gsxws.egg-info/SOURCES.txt
gsxws.egg-info/dependency_links.txt
gsxws.egg-info/requires.txt
gsxws.egg-info/top_level.txt
tests/__init__.py
tests/test_gsxws.py