Metadata-Version: 2.1
Name: gsxws
Version: 0.94
Summary: Library for communicating with GSX Web Services API.
Home-page: https://github.com/filipp/py-gsxws
Author: Filipp Lepalaan
Author-email: filipp@fps.ee
License: BSD
Download-URL: https://github.com/filipp/py-gsxws/tarball/latest
Keywords: gsx,python
Platform: UNKNOWN
Classifier: Environment :: Web Environment
Classifier: Intended Audience :: Developers
Classifier: License :: OSI Approved :: BSD License
Classifier: Operating System :: OS Independent
Classifier: Programming Language :: Python
Classifier: Topic :: Internet :: WWW/HTTP
